pytest_server_fixtures/__init__.py
pytest_server_fixtures/base.py
pytest_server_fixtures/base2.py
pytest_server_fixtures/http.py
pytest_server_fixtures/httpd.py
pytest_server_fixtures/jenkins.py
pytest_server_fixtures/mongo.py
pytest_server_fixtures/postgres.py
pytest_server_fixtures/redis.py
pytest_server_fixtures/s3.py
pytest_server_fixtures/util.py
pytest_server_fixtures/xvfb.py
pytest_server_fixtures/serverclass/__init__.py
pytest_server_fixtures/serverclass/common.py
pytest_server_fixtures/serverclass/docker.py
pytest_server_fixtures/serverclass/kubernetes.py
pytest_server_fixtures/serverclass/thread.py
pytest_server_fixtures-1.8.1.dist-info/LICENSE
pytest_server_fixtures-1.8.1.dist-info/METADATA
pytest_server_fixtures-1.8.1.dist-info/WHEEL
pytest_server_fixtures-1.8.1.dist-info/entry_points.txt
pytest_server_fixtures-1.8.1.dist-info/top_level.txt
pytest_server_fixtures-1.8.1.dist-info/RECORD
