Metadata-Version: 2.1
Name: pytest-server-fixtures
Version: 1.8.1
Summary: Extensible server fixtures for py.test
Home-page: https://github.com/man-group/pytest-plugins
Author: Edward Easton
Author-email: eeaston@gmail.com
License: MIT license
Platform: unix
Platform: linux
Classifier: License :: OSI Approved :: MIT License
Classifier: Development Status :: 5 - Production/Stable
Classifier: Topic :: Software Development :: Libraries
Classifier: Topic :: Software Development :: Testing
Classifier: Topic :: Utilities
Classifier: Intended Audience :: Developers
Classifier: Operating System :: POSIX
Classifier: Programming Language :: Python :: 3.6
Classifier: Programming Language :: Python :: 3.7
Requires-Python: >=3.6
Provides-Extra: jenkins
Provides-Extra: mongodb
Provides-Extra: postgres
Provides-Extra: redis
Provides-Extra: s3
Provides-Extra: docker
Provides-Extra: kubernetes
License-File: LICENSE
